{"timestamp": "Thu Jul 29 19:05:28 2021", "loosers": [{"ticker": "SAVA", "name": "Cassava Sciences, Inc.", "change": "-18.01%"}, {"ticker": "QFIN", "name": "360 DigiTech, Inc.", "change": "-17.39%"}, {"ticker": "ALEC", "name": "Alector, Inc.", "change": "-16.52%"}, {"ticker": "CTXS", "name": "Citrix Systems, Inc.", "change": "-14.13%"}, {"ticker": "CHUC", "name": "Charlie's Holdings, Inc.", "change": "-13.79%"}, {"ticker": "BCAUY", "name": "Brilliance China Automotive Holdings Limited", "change": "-12.74%"}, {"ticker": "CMPR", "name": "Cimpress plc", "change": "-11.92%"}, {"ticker": "NVCR", "name": "NovoCure Limited", "change": "-11.12%"}, {"ticker": "BEKE", "name": "KE Holdings Inc.", "change": "-11.64%"}, {"ticker": "NKLA", "name": "Nikola Corporation", "change": "-10.61%"}, {"ticker": "EQT", "name": "EQT Corporation", "change": "-9.13%"}, {"ticker": "DDL", "name": "Dingdong (Cayman) Limited", "change": "-8.81%"}, {"ticker": "GSHD", "name": "Goosehead Insurance, Inc", "change": "-8.35%"}, {"ticker": "ATUS", "name": "Altice USA, Inc.", "change": "-8.28%"}, {"ticker": "PTC", "name": "PTC Inc.", "change": "-7.86%"}, {"ticker": "ME", "name": "23andMe Holding Co.", "change": "-7.27%"}, {"ticker": "CLVT", "name": "Clarivate Plc", "change": "-6.79%"}, {"ticker": "TAL", "name": "TAL Education Group", "change": "-6.88%"}, {"ticker": "LU", "name": "Lufax Holding Ltd", "change": "-6.30%"}, {"ticker": "PRLB", "name": "Proto Labs, Inc.", "change": "-6.04%"}, {"ticker": "SNN", "name": "Smith & Nephew plc", "change": "-5.95%"}, {"ticker": "BODY", "name": "The Beachbody Company, Inc.", "change": "-5.60%"}, {"ticker": "SBH", "name": "Sally Beauty Holdings, Inc.", "change": "-5.64%"}, {"ticker": "QS", "name": "QuantumScape Corporation", "change": "-5.60%"}, {"ticker": "PEGA", "name": "Pegasystems Inc.", "change": "-5.51%"}]}