{"timestamp": "Mon Jul 19 19:05:37 2021", "loosers": [{"ticker": "RLLCF", "name": "Rolls-Royce Holdings plc", "change": "-18.59%"}, {"ticker": "NEGG", "name": "Newegg Commerce, Inc.", "change": "-16.30%"}, {"ticker": "CITAF", "name": "COSCO SHIPPING Development Co., Ltd.", "change": "-15.87%"}, {"ticker": "LLDTF", "name": "Lloyds Banking Group plc", "change": "-10.97%"}, {"ticker": "CAHPF", "name": "Evolution Mining Limited", "change": "-10.72%"}, {"ticker": "MTDR", "name": "Matador Resources Company", "change": "-10.52%"}, {"ticker": "YALA", "name": "Yalla Group Limited", "change": "-10.12%"}, {"ticker": "BHG", "name": "Bright Health Group, Inc.", "change": "-9.60%"}, {"ticker": "SEAS", "name": "SeaWorld Entertainment, Inc.", "change": "-9.02%"}, {"ticker": "AEVA", "name": "Aeva Technologies, Inc.", "change": "-8.70%"}, {"ticker": "NSRXF", "name": "Nomad Royalty Company Ltd.", "change": "-8.73%"}, {"ticker": "SIX", "name": "Six Flags Entertainment Corporation", "change": "-8.63%"}, {"ticker": "PDCE", "name": "PDC Energy, Inc.", "change": "-8.09%"}, {"ticker": "CIG-C", "name": "Companhia Energ\u00e9tica de Minas Gerais", "change": "-8.05%"}, {"ticker": "AGTI", "name": "Agiliti, Inc.", "change": "-7.60%"}, {"ticker": "PPERF", "name": "PT Bank Mandiri (Persero) Tbk", "change": "-7.96%"}, {"ticker": "BLMN", "name": "Bloomin' Brands, Inc.", "change": "-7.90%"}, {"ticker": "FQVLF", "name": "First Quantum Minerals Ltd.", "change": "-7.84%"}, {"ticker": "ARGGY", "name": "Aston Martin Lagonda Global Holdings plc", "change": "-7.75%"}, {"ticker": "VAL", "name": "Valaris Limited", "change": "-8.02%"}, {"ticker": "ZIP", "name": "ZipRecruiter, Inc.", "change": "-7.61%"}, {"ticker": "FANG", "name": "Diamondback Energy, Inc.", "change": "-7.64%"}, {"ticker": "TECK", "name": "Teck Resources Limited", "change": "-7.47%"}, {"ticker": "ANGI", "name": "Angi Inc.", "change": "-7.30%"}, {"ticker": "SM", "name": "SM Energy Company", "change": "-7.34%"}]}