{"timestamp": "Fri Jul 16 19:05:38 2021", "loosers": [{"ticker": "TRQ", "name": "Turquoise Hill Resources Ltd.", "change": "-15.36%"}, {"ticker": "DFIFF", "name": "Diamond Fields Resources Inc.", "change": "-14.00%"}, {"ticker": "RLLCF", "name": "Rolls-Royce Holdings plc", "change": "-13.36%"}, {"ticker": "GOTU", "name": "Gaotu Techedu Inc.", "change": "-10.94%"}, {"ticker": "TAL", "name": "TAL Education Group", "change": "-10.76%"}, {"ticker": "RLX", "name": "RLX Technology Inc.", "change": "-10.41%"}, {"ticker": "ERIC", "name": "Telefonaktiebolaget LM Ericsson (publ)", "change": "-10.45%"}, {"ticker": "ERIXF", "name": "Telefonaktiebolaget LM Ericsson (publ)", "change": "-9.86%"}, {"ticker": "FQVLF", "name": "First Quantum Minerals Ltd.", "change": "-9.69%"}, {"ticker": "WISH", "name": "ContextLogic Inc.", "change": "-8.74%"}, {"ticker": "ZLAB", "name": "Zai Lab Limited", "change": "-8.21%"}, {"ticker": "LTHM", "name": "Livent Corporation", "change": "-7.82%"}, {"ticker": "CLF", "name": "Cleveland-Cliffs Inc.", "change": "-7.54%"}, {"ticker": "TROX", "name": "Tronox Holdings plc", "change": "-6.79%"}, {"ticker": "AG", "name": "First Majestic Silver Corp.", "change": "-7.17%"}, {"ticker": "TDC", "name": "Teradata Corporation", "change": "-6.94%"}, {"ticker": "BHG", "name": "Bright Health Group, Inc.", "change": "-6.85%"}, {"ticker": "IGT", "name": "International Game Technology PLC", "change": "-6.51%"}, {"ticker": "DLO", "name": "DLocal Limited", "change": "-6.93%"}, {"ticker": "VTSYF", "name": "Vitasoy International Holdings Limited", "change": "-6.38%"}, {"ticker": "ASTR", "name": "Astra Space, Inc.", "change": "-5.95%"}, {"ticker": "PSMMF", "name": "Persimmon Plc", "change": "-6.18%"}, {"ticker": "IVPAF", "name": "Ivanhoe Mines Ltd.", "change": "-6.06%"}, {"ticker": "VNET", "name": "21Vianet Group, Inc.", "change": "-5.94%"}, {"ticker": "FLR", "name": "Fluor Corporation", "change": "-5.71%"}]}