{"timestamp": "Thu Jun 10 19:19:10 2021", "loosers": [{"ticker": "GME", "name": "GameStop Corp.", "change": "-28.61%"}, {"ticker": "CLOV", "name": "Clover Health Investments, Corp.", "change": "-17.32%"}, {"ticker": "CELH", "name": "Celsius Holdings, Inc.", "change": "-16.22%"}, {"ticker": "CLNE", "name": "Clean Energy Fuels Corp.", "change": "-15.14%"}, {"ticker": "AMC", "name": "AMC Entertainment Holdings, Inc.", "change": "-12.93%"}, {"ticker": "KC", "name": "Kingsoft Cloud Holdings Limited", "change": "-11.33%"}, {"ticker": "ROOT", "name": "Root, Inc.", "change": "-11.02%"}, {"ticker": "QS", "name": "QuantumScape Corporation", "change": "-11.28%"}, {"ticker": "ESALY", "name": "Eisai Co., Ltd.", "change": "-11.15%"}, {"ticker": "CCS", "name": "Century Communities, Inc.", "change": "-10.97%"}, {"ticker": "FCEL", "name": "FuelCell Energy, Inc.", "change": "-10.34%"}, {"ticker": "BBBY", "name": "Bed Bath & Beyond Inc.", "change": "-9.86%"}, {"ticker": "EXPI", "name": "eXp World Holdings, Inc.", "change": "-8.65%"}, {"ticker": "DFH", "name": "Dream Finders Homes, Inc.", "change": "-8.69%"}, {"ticker": "CAKE", "name": "The Cheesecake Factory Incorporated", "change": "-7.96%"}, {"ticker": "TGLVY", "name": "Top Glove Corporation Bhd.", "change": "-8.03%"}, {"ticker": "LDI", "name": "loanDepot, Inc.", "change": "-7.77%"}, {"ticker": "BB", "name": "BlackBerry Limited", "change": "-7.83%"}, {"ticker": "LGIH", "name": "LGI Homes, Inc.", "change": "-8.05%"}, {"ticker": "LTHM", "name": "Livent Corporation", "change": "-6.93%"}, {"ticker": "TSP", "name": "TuSimple Holdings Inc.", "change": "-6.93%"}, {"ticker": "OSCR", "name": "Oscar Health, Inc.", "change": "-6.48%"}, {"ticker": "AI", "name": "C3.ai, Inc.", "change": "-6.54%"}, {"ticker": "IAA", "name": "IAA, Inc.", "change": "-6.66%"}, {"ticker": "DDS", "name": "Dillard's, Inc.", "change": "-6.53%"}]}