{"timestamp": "Fri Jul  2 14:06:16 2021", "loosers": [{"ticker": "ARWR", "name": "Arrowhead Pharmaceuticals, Inc.", "change": "-24.61%"}, {"ticker": "AAGH", "name": "America Great Health", "change": "-9.16%"}, {"ticker": "CRCT", "name": "Cricut, Inc.", "change": "-9.54%"}, {"ticker": "CERE", "name": "Cerevel Therapeutics Holdings, Inc.", "change": "-8.64%"}, {"ticker": "GOTU", "name": "Gaotu Techedu Inc.", "change": "-8.84%"}, {"ticker": "BDRBF", "name": "Bombardier Inc.", "change": "-7.08%"}, {"ticker": "TAL", "name": "TAL Education Group", "change": "-7.46%"}, {"ticker": "BDRAF", "name": "Bombardier Inc.", "change": "-6.79%"}, {"ticker": "KC", "name": "Kingsoft Cloud Holdings Limited", "change": "-6.56%"}, {"ticker": "VSTO", "name": "Vista Outdoor Inc.", "change": "-6.47%"}, {"ticker": "CLOV", "name": "Clover Health Investments, Corp.", "change": "-6.04%"}, {"ticker": "AMC", "name": "AMC Entertainment Holdings, Inc.", "change": "-5.81%"}, {"ticker": "LI", "name": "Li Auto Inc.", "change": "-5.77%"}, {"ticker": "OPK", "name": "OPKO Health, Inc.", "change": "-5.90%"}, {"ticker": "SRNE", "name": "Sorrento Therapeutics, Inc.", "change": "-5.46%"}, {"ticker": "ZIM", "name": "ZIM Integrated Shipping Services Ltd.", "change": "-4.66%"}, {"ticker": "BFLY", "name": "Butterfly Network, Inc.", "change": "-4.91%"}, {"ticker": "FINV", "name": "FinVolution Group", "change": "-4.61%"}, {"ticker": "SBLK", "name": "Star Bulk Carriers Corp.", "change": "-3.70%"}, {"ticker": "MFGP", "name": "Micro Focus International plc", "change": "-4.11%"}, {"ticker": "EDIT", "name": "Editas Medicine, Inc.", "change": "-4.29%"}, {"ticker": "CVAC", "name": "CureVac N.V.", "change": "-3.99%"}, {"ticker": "CPG", "name": "Crescent Point Energy Corp.", "change": "-3.66%"}, {"ticker": "HIMX", "name": "Himax Technologies, Inc.", "change": "-3.65%"}, {"ticker": "RLX", "name": "RLX Technology Inc.", "change": "-3.71%"}]}